ai_assistant/__init__.py
ai_assistant/ai_assistant.py
ai_assistant/prompts.json
ai_assistant/assistant/__init__.py
ai_assistant/assistant/baimiao_ocr.py
ai_assistant/assistant/base.py
ai_assistant/assistant/chat_with_tts_no_stream.py
ai_assistant/assistant/chat_with_tts_stream.py
ai_assistant/assistant/image_generator.py
ai_assistant/assistant/openai_model.py
ai_assistant/assistant/openai_tts.py
ai_assistant/assistant/piclab_uploader.py
ai_assistant/assistant/qwen_model.py
ai_assistant/assistant/qwq_model.py
ai_assistant/assistant/screenshot_ocr_llm.py
ai_assistant/assistant/screenshot_piclab_uploader.py
ai_assistant/assistant/tts_client.py
ai_assistant/assistant/tts_server.py
multi_ai_assistant-1.1.3.dist-info/licenses/LICENSE
multi_ai_assistant-1.1.3.dist-info/METADATA
multi_ai_assistant-1.1.3.dist-info/WHEEL
multi_ai_assistant-1.1.3.dist-info/entry_points.txt
multi_ai_assistant-1.1.3.dist-info/top_level.txt
multi_ai_assistant-1.1.3.dist-info/RECORD
