Metadata-Version: 2.4
Name: multi-ai-assistant
Version: 1.1.3
Summary: A Python-based AI assistant project
Author: mofanx
License-Expression: MIT
Requires-Python: >=3.8
License-File: LICENSE
Requires-Dist: keyboard
Requires-Dist: pygame
Requires-Dist: asyncio
Requires-Dist: requests
Requires-Dist: openai
Requires-Dist: pyclip
Requires-Dist: aiohttp
Dynamic: license-file
